sandboxie/__init__.py
sandboxie/sandboxie.py
sandboxie/sbieini.py
pysbie-1.0.0.dist-info/LICENSE.md
pysbie-1.0.0.dist-info/METADATA
pysbie-1.0.0.dist-info/WHEEL
pysbie-1.0.0.dist-info/top_level.txt
pysbie-1.0.0.dist-info/RECORD
