Metadata-Version: 2.1
Name: pysbie
Version: 1.0.0
Summary: Interact with Sandboxie in Python
Home-page: https://github.com/Dzhigit/pysbie
Author: Dzhigit
Author-email: dzhigitabdualah@gmail.com
Keywords: sandboxie python
Classifier: Programming Language :: Python :: 3.12
Classifier: License :: OSI Approved :: GNU General Public License (GPL)
Classifier: Operating System :: OS Independent
Requires-Python: >=3.9
License-File: LICENSE.md
Requires-Dist: requests
